pyinterface/__init__.py
pyinterface/core.py
pyinterface/gpg2000.py
pyinterface/gpg3100.py
pyinterface/gpg3300.py
pyinterface/gpg6204.py
pyinterface/gpg7204.py
pyinterface/gpg7400.py
pyinterface/pci2702.py
pyinterface/pci2724.py
pyinterface/pci3165.py
pyinterface/pci3177.py
pyinterface/pci3342.py
pyinterface/pci3346.py
pyinterface/pci340516.py
pyinterface/pci340816.py
pyinterface/pci6204.py
pyinterface/pci7204.py
pyinterface/pci7415.py
pyinterface/tools.py
pyinterface-1.7.5.dist-info/LICENSE.txt
pyinterface-1.7.5.dist-info/METADATA
pyinterface-1.7.5.dist-info/WHEEL
pyinterface-1.7.5.dist-info/top_level.txt
pyinterface-1.7.5.dist-info/RECORD
