Metadata-Version: 2.1
Name: pyinterface
Version: 1.7.5
Summary: driver for Interface PCI board
Home-page: https://github.com/ogawa-ros/pyinterface
Author: Atsushi Nishimura
Author-email: ars096@gmail.com
License: MIT
Project-URL: Documentation, https://pyinterface.readthedocs.io/
Project-URL: Source Code, https://github.com/ogawa-ros/pyinterface
Classifier: Operating System :: POSIX :: Linux
Classifier: Programming Language :: Python
Classifier: Programming Language :: Python :: 3
Classifier: License :: OSI Approved :: MIT License
Classifier: Topic :: Software Development :: Libraries :: Python Modules
Classifier: Topic :: System :: Hardware
License-File: LICENSE.txt
Requires-Dist: portio
Requires-Dist: pypci
Requires-Dist: psutil
Requires-Dist: importlib-metadata ; python_version < "3.8"
